MANIFEST.in
README.md
requirements.txt
setup.cfg
setup.py
tuijam/__init__.py
tuijam/app.py
tuijam/lastfm.py
tuijam/mpris.py
tuijam/music_objects.py
tuijam/ui.py
tuijam/utility.py
tuijam.egg-info/PKG-INFO
tuijam.egg-info/SOURCES.txt
tuijam.egg-info/dependency_links.txt
tuijam.egg-info/entry_points.txt
tuijam.egg-info/requires.txt
tuijam.egg-info/top_level.txt